roosevelt/__init__.py
roosevelt/code.py
roosevelt/constiuency.py
roosevelt/corpus.py
roosevelt/dependency.py
roosevelt/grams.py
roosevelt/polarity.py
roosevelt/pos.py
roosevelt/rule.py
roosevelt/smoothing.py
roosevelt/stemming.py
roosevelt/stopwords.py
roosevelt/tokenizer.py
roosevelt/wordcount.py
roosevelt-0.2.0.dist-info/METADATA
roosevelt-0.2.0.dist-info/WHEEL
roosevelt-0.2.0.dist-info/top_level.txt
roosevelt-0.2.0.dist-info/RECORD
