Metadata-Version: 2.4
Name: roosevelt
Version: 0.2.0
Summary: A sample Python package
Author-email: Capy Bara <capyslayers@gmail.com>
Requires-Dist: IPython
